main.py
mcp_ops_toolkit_lushiping-0.1.0.dist-info/METADATA
mcp_ops_toolkit_lushiping-0.1.0.dist-info/WHEEL
mcp_ops_toolkit_lushiping-0.1.0.dist-info/top_level.txt
mcp_ops_toolkit_lushiping-0.1.0.dist-info/RECORD
