Metadata-Version: 2.4
Name: mcp-ops-toolkit_lushiping
Version: 0.1.0
Summary: A toolkit for MCP operations
Author-email: lushiping <lsp20231128@gmail.com>
License-Expression: MIT
Project-URL: Homepage, https://github.com/luashiping/mcp-ops-toolkit
Project-URL: Repository, https://github.com/luashiping/mcp-ops-toolkit.git
Classifier: Development Status :: 3 - Alpha
Classifier: Intended Audience :: Developers
Classifier: Programming Language :: Python :: 3
Classifier: Programming Language :: Python :: 3.11
Requires-Python: >=3.11.7
Requires-Dist: mcp[cli]>=1.6.0
Requires-Dist: openpyxl>=3.1.5
Requires-Dist: pandas>=2.2.3
